demo_py_lib/__init__.py
demo_py_lib-0.1.0.dist-info/METADATA
demo_py_lib-0.1.0.dist-info/WHEEL
demo_py_lib-0.1.0.dist-info/RECORD
